element/__init__.py
element/errors.py
element/matrix_client/__init__.py
element/matrix_client/api.py
element/matrix_client/checks.py
element/matrix_client/client.py
element/matrix_client/errors.py
element/matrix_client/room.py
element/matrix_client/user.py
element/matrix_client/crypto/__init__.py
element/matrix_client/crypto/olm_device.py
element/matrix_client/crypto/one_time_keys.py
element-sdk/__init__.py
element-sdk/errors.py
element-sdk/matrix_client/__init__.py
element-sdk/matrix_client/api.py
element-sdk/matrix_client/checks.py
element-sdk/matrix_client/client.py
element-sdk/matrix_client/errors.py
element-sdk/matrix_client/room.py
element-sdk/matrix_client/user.py
element-sdk/matrix_client/crypto/__init__.py
element-sdk/matrix_client/crypto/olm_device.py
element-sdk/matrix_client/crypto/one_time_keys.py
element_sdk-0.2.5.dist-info/METADATA
element_sdk-0.2.5.dist-info/WHEEL
element_sdk-0.2.5.dist-info/top_level.txt
element_sdk-0.2.5.dist-info/RECORD
