Metadata-Version: 2.1
Name: element-sdk
Version: 0.2.5
Summary: Element.io SDK
Author: ierhon
Author-email: <ierhonl@proton.me>
Keywords: element,matrix,matrix_client,SDK,discord.py,bots
Classifier: Development Status :: 5 - Production/Stable
Classifier: Intended Audience :: Developers
Classifier: Programming Language :: Python :: 3
Classifier: Operating System :: Unix
Classifier: Operating System :: MacOS :: MacOS X
Classifier: Operating System :: Microsoft :: Windows
Requires-Dist: requests
